rirbind.cpython-39-x86_64-linux-gnu.so
examples/__init__.py
examples/pyroom.py
freqrir/__init__.py
freqrir/freqrir.py
freqrir/helper.py
freqrir/timerir.py
tests/__init__.py
tests/test_freqrir.py
tests/test_helper.py
tests/test_timerir.py
freqrir-0.0.4.dist-info/METADATA
freqrir-0.0.4.dist-info/WHEEL
freqrir-0.0.4.dist-info/top_level.txt
freqrir-0.0.4.dist-info/RECORD
