Metadata-Version: 2.1
Name: freqrir
Version: 0.0.4
Summary: A room impulse response generator using pybind11
Home-page: https://github.com/woodRock/freqRIR
Author: Jesse Wood
Author-email: j.r.h.wood98@gmail.com
License: MIT
Platform: UNKNOWN
Requires-Python: >=3.6
Provides-Extra: test
Requires-Dist: pytest ; extra == 'test'
